MANIFEST.in
README.rst
setup.py
src/collective/__init__.py
src/collective.gmaplocation.egg-info/PKG-INFO
src/collective.gmaplocation.egg-info/SOURCES.txt
src/collective.gmaplocation.egg-info/dependency_links.txt
src/collective.gmaplocation.egg-info/entry_points.txt
src/collective.gmaplocation.egg-info/namespace_packages.txt
src/collective.gmaplocation.egg-info/not-zip-safe
src/collective.gmaplocation.egg-info/requires.txt
src/collective.gmaplocation.egg-info/top_level.txt
src/collective/gmaplocation/__init__.py
src/collective/gmaplocation/configure.zcml
src/collective/gmaplocation/extender.py
src/collective/gmaplocation/interfaces.py
src/collective/gmaplocation/location.py
src/collective/gmaplocation/profile.zcml
src/collective/gmaplocation/properties.py
src/collective/gmaplocation/skins.zcml
src/collective/gmaplocation/utils.py
src/collective/gmaplocation/browser/__init__.py
src/collective/gmaplocation/browser/configure.zcml
src/collective/gmaplocation/browser/controlpanel.py
src/collective/gmaplocation/browser/controlpanel.yaml
src/collective/gmaplocation/browser/provider.py
src/collective/gmaplocation/browser/views.py
src/collective/gmaplocation/browser/gmaplocation/gmap_icon.png
src/collective/gmaplocation/browser/gmaplocation/location_view.pt
src/collective/gmaplocation/browser/images/location_icon.png
src/collective/gmaplocation/browser/images/maps_icon.png
src/collective/gmaplocation/browser/images/zoom_icon.png
src/collective/gmaplocation/browser/scripts/de.js
src/collective/gmaplocation/browser/scripts/main.js
src/collective/gmaplocation/browser/styles/main.css
src/collective/gmaplocation/browser/templates/authoring.pt
src/collective/gmaplocation/browser/templates/controlpanel.pt
src/collective/gmaplocation/browser/templates/info.pt
src/collective/gmaplocation/browser/templates/invocation.pt
src/collective/gmaplocation/browser/templates/map.pt
src/collective/gmaplocation/browser/templates/resources.pt
src/collective/gmaplocation/browser/templates/route.pt
src/collective/gmaplocation/locales/README.txt
src/collective/gmaplocation/locales/gmaplocation.pot
src/collective/gmaplocation/locales/de/LC_MESSAGES/gmaplocation.mo
src/collective/gmaplocation/locales/de/LC_MESSAGES/gmaplocation.po
src/collective/gmaplocation/profile/browserlayer.xml
src/collective/gmaplocation/profile/controlpanel.xml
src/collective/gmaplocation/profile/cssregistry.xml
