Metadata-Version: 1.0
Name: collective.gmaplocation
Version: 0.2
Summary: Plone Add-On to manage and display locations.
Home-page: UNKNOWN
Author: BlueDynamics Alliance
Author-email: dev@bluedynamics.com
License: GNU General Public Licence
Keywords: web zope plone google maps
Platform: UNKNOWN
Classifier: Framework :: Plone
Classifier: Programming Language :: Python
Classifier: Topic :: Software Development :: Libraries :: Python Modules
Classifier: License :: OSI Approved :: GNU General Public License (GPL)
